deepmriprep/__init__.py
deepmriprep/atlas.py
deepmriprep/data/icon.png
deepmriprep/data/patches.csv
deepmriprep/data/templates/Schaefer2018_100Parcels_17Networks_order.csv
deepmriprep/data/templates/Schaefer2018_100Parcels_17Networks_order.nii.gz
deepmriprep/data/templates/Schaefer2018_200Parcels_17Networks_order.csv
deepmriprep/data/templates/Schaefer2018_200Parcels_17Networks_order.nii.gz
deepmriprep/data/templates/Schaefer2018_400Parcels_17Networks_order.csv
deepmriprep/data/templates/Schaefer2018_400Parcels_17Networks_order.nii.gz
deepmriprep/data/templates/Schaefer2018_600Parcels_17Networks_order.csv
deepmriprep/data/templates/Schaefer2018_600Parcels_17Networks_order.nii.gz
deepmriprep/data/templates/Template_05mm_bet.nii.gz
deepmriprep/data/templates/Template_4_GS.nii.gz
deepmriprep/data/templates/aal3.csv
deepmriprep/data/templates/aal3.nii.gz
deepmriprep/data/templates/anatomy3.csv
deepmriprep/data/templates/anatomy3.nii.gz
deepmriprep/data/templates/cobra.csv
deepmriprep/data/templates/cobra.nii.gz
deepmriprep/data/templates/hammers.csv
deepmriprep/data/templates/hammers.nii.gz
deepmriprep/data/templates/ibsr.csv
deepmriprep/data/templates/ibsr.nii.gz
deepmriprep/data/templates/julichbrain.csv
deepmriprep/data/templates/julichbrain.nii.gz
deepmriprep/data/templates/lpba40.csv
deepmriprep/data/templates/lpba40.nii.gz
deepmriprep/data/templates/mori.csv
deepmriprep/data/templates/mori.nii.gz
deepmriprep/data/templates/neuromorphometrics.csv
deepmriprep/data/templates/neuromorphometrics.nii.gz
deepmriprep/data/templates/suit.csv
deepmriprep/data/templates/suit.nii.gz
deepmriprep/data/templates/thalamic_nuclei.csv
deepmriprep/data/templates/thalamic_nuclei.nii.gz
deepmriprep/data/templates/thalamus.csv
deepmriprep/data/templates/thalamus.nii.gz
deepmriprep/preprocess.py
deepmriprep/register.py
deepmriprep/segment.py
deepmriprep/smooth.py
deepmriprep/ui/__init__.py
deepmriprep/ui/cli.py
deepmriprep/ui/gui.py
deepmriprep/utils.py
deepmriprep-0.3.0.dist-info/LICENSE
deepmriprep-0.3.0.dist-info/METADATA
deepmriprep-0.3.0.dist-info/WHEEL
deepmriprep-0.3.0.dist-info/entry_points.txt
deepmriprep-0.3.0.dist-info/RECORD
