Metadata-Version: 2.3
Name: deepmriprep
Version: 0.3.0
Summary: Neural network-based preprocessing of MRI data: Prepping brain images in seconds 🔥
License: MIT
Author: codingfisch
Author-email: l_fisc17@wwu.de
Requires-Python: >=3.9,<4.0
Classifier: Intended Audience :: Science/Research
Classifier: License :: OSI Approved :: MIT License
Classifier: Operating System :: OS Independent
Classifier: Programming Language :: Python :: 3
Classifier: Programming Language :: Python :: 3.9
Classifier: Programming Language :: Python :: 3.10
Classifier: Programming Language :: Python :: 3.11
Classifier: Programming Language :: Python :: 3.12
Classifier: Programming Language :: Python :: 3.13
Requires-Dist: deepbet (>=1.0.2)
Requires-Dist: requests
Requires-Dist: spline-resize (>=0.1.1)
Requires-Dist: torch (>=1.11.0)
Requires-Dist: torchreg (>=0.1.3)
Project-URL: Repository, https://github.com/wwu-mmll/deepmriprep
